ligo/scald/__init__.py
ligo/scald/__main__.py
ligo/scald/aggregator.py
ligo/scald/deploy.py
ligo/scald/mock.py
ligo/scald/report.py
ligo/scald/resources.py
ligo/scald/serve.py
ligo/scald/transforms.py
ligo/scald/utils.py
ligo/scald/io/__init__.py
ligo/scald/io/core.py
ligo/scald/io/influx.py
ligo/scald/io/kafka.py
ligo/scald/io/line_protocol.py
ligo/scald/static/bns-light.jpg
ligo/scald/static/favicon.ico
ligo/scald/static/scald.css
ligo/scald/static/scald.js
ligo/scald/templates/content.html
ligo/scald/templates/dashboard.html
ligo/scald/templates/ifar_table.html
ligo/scald/templates/navbar.html
ligo/scald/templates/plots.html
ligo/scald/templates/report.html
ligo/scald/templates/report_navbar.html
ligo/scald/templates/report_scripts.js
ligo/scald/templates/scripts.js
ligo/scald/tests/__init__.py
ligo/scald/tests/conftest.py
ligo/scald/tests/test_io.py
ligo/scald/tests/test_mock.py
ligo/scald/tests/test_report.py
ligo/scald/tests/test_resources.py
ligo/scald/tests/test_transforms.py
ligo/scald/tests/test_utils.py
ligo_scald-0.8.5.dist-info/licenses/LICENSE
ligo_scald-0.8.5.dist-info/METADATA
ligo_scald-0.8.5.dist-info/WHEEL
ligo_scald-0.8.5.dist-info/entry_points.txt
ligo_scald-0.8.5.dist-info/top_level.txt
ligo_scald-0.8.5.dist-info/RECORD
