Metadata-Version: 2.4
Name: ligo-scald
Version: 0.8.5
Summary: SCalable Analytics for LVK Data
Home-page: https://git.ligo.org/gstlal-visualisation/ligo-scald
Author: Olivia Godwin
Author-email: olivia.godwin@ligo.org
Maintainer: Olivia Godwin
Maintainer-email: olivia.godwin@ligo.org
License: GPL-2.0-or-later
Project-URL: Bug Tracker, https://git.ligo.org/gstlal-visualisation/ligo-scald/issues/
Project-URL: Source Code, https://git.ligo.org/gstlal-visualisation/ligo-scald.git
Classifier: Development Status :: 4 - Beta
Classifier: Programming Language :: Python
Classifier: Programming Language :: Python :: 3
Classifier: Intended Audience :: Science/Research
Classifier: Intended Audience :: End Users/Desktop
Classifier: Intended Audience :: Developers
Classifier: Natural Language :: English
Classifier: Topic :: Scientific/Engineering
Classifier: Topic :: Scientific/Engineering :: Astronomy
Classifier: Topic :: Scientific/Engineering :: Physics
Classifier: Operating System :: POSIX
Classifier: Operating System :: Unix
Classifier: Operating System :: MacOS
Classifier: License :: OSI Approved :: GNU General Public License v2 or later (GPLv2+)
Requires-Python: >=3.6
License-File: LICENSE
Requires-Dist: bottle>=0.12
Requires-Dist: numpy>=1.7
Requires-Dist: PyYAML>=3.10
Requires-Dist: urllib3>=1.10
Requires-Dist: python-dateutil
Provides-Extra: aggregate
Requires-Dist: confluent-kafka>=0.11.4; extra == "aggregate"
Dynamic: license-file
